{
  "$schema": "https://developer.microsoft.com/json-schemas/fabric/item/report/definition/visualContainer/2.10.0/schema.json",
  "name": "cc47e6715a2b990ac63c",
  "position": {
    "x": 155.06055377812024,
    "y": 107.03294862560513,
    "z": 0,
    "height": 348.54319167825258,
    "width": 484.39270339536677,
    "tabOrder": 0
  },
  "visual": {
    "visualType": "clusteredColumnChart",
    "query": {
      "queryState": {
        "Category": {
          "projections": [
            {
              "field": {
                "Column": {
                  "Expression": {
                    "SourceRef": {
                      "Entity": "sample_sales_dataset"
                    }
                  },
                  "Property": "Product"
                }
              },
              "queryRef": "sample_sales_dataset.Product",
              "nativeQueryRef": "Product",
              "active": true
            }
          ]
        },
        "Y": {
          "projections": [
            {
              "field": {
                "Aggregation": {
                  "Expression": {
                    "Column": {
                      "Expression": {
                        "SourceRef": {
                          "Entity": "sample_sales_dataset"
                        }
                      },
                      "Property": "Total_Amount"
                    }
                  },
                  "Function": 0
                }
              },
              "queryRef": "Sum(sample_sales_dataset.Total_Amount)",
              "nativeQueryRef": "Sum of Total_Amount"
            }
          ]
        }
      },
      "sortDefinition": {
        "sort": [
          {
            "field": {
              "Aggregation": {
                "Expression": {
                  "Column": {
                    "Expression": {
                      "SourceRef": {
                        "Entity": "sample_sales_dataset"
                      }
                    },
                    "Property": "Total_Amount"
                  }
                },
                "Function": 0
              }
            },
            "direction": "Descending"
          }
        ],
        "isDefaultSort": true
      }
    },
    "drillFilterOtherVisuals": true
  },
  "filterConfig": {
    "filters": [
      {
        "name": "f42ae4a5a08da8e5a10b",
        "field": {
          "Column": {
            "Expression": {
              "SourceRef": {
                "Entity": "sample_sales_dataset"
              }
            },
            "Property": "Product"
          }
        },
        "type": "Categorical"
      },
      {
        "name": "200dac165a5a247b47da",
        "field": {
          "Aggregation": {
            "Expression": {
              "Column": {
                "Expression": {
                  "SourceRef": {
                    "Entity": "sample_sales_dataset"
                  }
                },
                "Property": "Total_Amount"
              }
            },
            "Function": 0
          }
        },
        "type": "Advanced"
      }
    ]
  }
}